INSTALL.rst
LICENSE
MANIFEST.in
README.rst
VERSION
requirements.txt
setup.py
tasks.py
src/miniserver/__init__.py
src/miniserver/__main__.py
src/miniserver/__meta__.py
src/miniserver/logger.py
src/miniserver/manage.py
src/miniserver/models.py
src/miniserver/routes.py
src/miniserver/runners.py
src/miniserver/settings.py
src/miniserver/views.py
src/miniserver.egg-info/PKG-INFO
src/miniserver.egg-info/SOURCES.txt
src/miniserver.egg-info/dependency_links.txt
src/miniserver.egg-info/entry_points.txt
src/miniserver.egg-info/not-zip-safe
src/miniserver.egg-info/requires.txt
src/miniserver.egg-info/top_level.txt
src/miniserver/django_project/__init__.py
src/miniserver/django_project/settings.py
src/miniserver/django_project/urls.py
src/miniserver/django_project/wsgi.py
src/miniserver/miniserver_app/__init__.py
src/miniserver/miniserver_app/admin.py
src/miniserver/miniserver_app/apps.py
src/miniserver/miniserver_app/models.py
src/miniserver/miniserver_app/tests.py
src/miniserver/miniserver_app/views.py
src/miniserver/miniserver_app/migrations/0001_initial.py
src/miniserver/miniserver_app/migrations/0002_auto_20170326_0503.py
src/miniserver/miniserver_app/migrations/__init__.py
src/miniserver/tests/__init__.py
src/miniserver/tests/__main__.py
src/miniserver/tests/test_documentation.py
src/miniserver/tests/test_miniserver.py